{
  "total_repos_analyzed": 124,
  "total_lines_added": 1018780,
  "total_commits": 2277,
  "languages": [
    {
      "name": "TypeScript",
      "lines_added": 626521,
      "percentage": 61.5,
      "color": "#3178c6"
    },
    {
      "name": "JavaScript",
      "lines_added": 237829,
      "percentage": 23.3,
      "color": "#f1e05a"
    },
    {
      "name": "Python",
      "lines_added": 93345,
      "percentage": 9.2,
      "color": "#3572A5"
    },
    {
      "name": "Dart",
      "lines_added": 47826,
      "percentage": 4.7,
      "color": "#00B4AB"
    },
    {
      "name": "SQL",
      "lines_added": 4717,
      "percentage": 0.5,
      "color": "#e38c00"
    },
    {
      "name": "Shell",
      "lines_added": 4068,
      "percentage": 0.4,
      "color": "#89e051"
    },
    {
      "name": "C++",
      "lines_added": 3622,
      "percentage": 0.4,
      "color": "#f34b7d"
    },
    {
      "name": "C#",
      "lines_added": 402,
      "percentage": 0.0,
      "color": "#178600"
    },
    {
      "name": "Swift",
      "lines_added": 259,
      "percentage": 0.0,
      "color": "#F05138"
    },
    {
      "name": "Rust",
      "lines_added": 149,
      "percentage": 0.0,
      "color": "#dea584"
    }
  ],
  "_cache": {
    "BassRhombus/BassRhombus": {
      "last_sha": "8a7799379f6bea6a99d589b4a0f60561532adc65",
      "total_commits": 235,
      "total_lines": 926,
      "lang_lines": {
        "Python": 926
      }
    },
    "BassRhombus/primal-overlay": {
      "last_sha": "c77e7427f0bed2e6cb4c3512c7eee406d5568bea",
      "total_commits": 2,
      "total_lines": 2039,
      "lang_lines": {
        "JavaScript": 2039
      }
    },
    "Arvo-OFM/ofmanager-api": {
      "last_sha": "f14bdc23ac3f501901258f176445e6c112ae1183",
      "total_commits": 172,
      "total_lines": 66122,
      "lang_lines": {
        "TypeScript": 64511,
        "SQL": 1059,
        "JavaScript": 552
      }
    },
    "Arvo-OFM/betterfans": {
      "last_sha": "be8389f0b5f6449ad661c9a64e22e1b2de9c1dd2",
      "total_commits": 1,
      "total_lines": 3,
      "lang_lines": {
        "TypeScript": 3
      }
    },
    "Arvo-Devs/ofmanager-apps": {
      "last_sha": "348e0a6c81c5a876f9e959c77733c1187494837a",
      "total_commits": 227,
      "total_lines": 267695,
      "lang_lines": {
        "TypeScript": 267296,
        "JavaScript": 399
      }
    },
    "BassRhombus/primal-deathmatch": {
      "last_sha": "28cf13d35e070aaee8ee29044d1264d4bae26ed5",
      "total_commits": 5,
      "total_lines": 16885,
      "lang_lines": {
        "Python": 16885
      }
    },
    "BassRhombus/primal-backend": {
      "last_sha": "83edca338bc3d492e8cbe0a7e25ab8e7e1563995",
      "total_commits": 7,
      "total_lines": 28059,
      "lang_lines": {
        "Python": 27248,
        "SQL": 811
      }
    },
    "BassRhombus/primal-workers": {
      "last_sha": "834a7084598b3d23a5cce991f8ea50cd2a863cd6",
      "total_commits": 4,
      "total_lines": 3046,
      "lang_lines": {
        "Python": 3046
      }
    },
    "BassRhombus/primal-web": {
      "last_sha": "de2981836c0a471d62607f246701bdc85776f637",
      "total_commits": 5,
      "total_lines": 38142,
      "lang_lines": {
        "TypeScript": 37547,
        "Python": 329,
        "JavaScript": 266
      }
    },
    "BassRhombus/primal-survival": {
      "last_sha": "c4cc556c04dc223ebae150848cdc3595582abab7",
      "total_commits": 3,
      "total_lines": 4151,
      "lang_lines": {
        "Python": 4151
      }
    },
    "BassRhombus/primal-discord": {
      "last_sha": "91f42a8f1e74cc2a0394d21d827a93bf392ee0b1",
      "total_commits": 3,
      "total_lines": 12279,
      "lang_lines": {
        "Python": 12279
      }
    },
    "Arvo-Devs/onlysearch": {
      "last_sha": "18eb03f4f0df2cf6b1f813ea0c492f73a0779cda",
      "total_commits": 43,
      "total_lines": 7648,
      "lang_lines": {
        "TypeScript": 7648
      }
    },
    "Taskiry/api": {
      "last_sha": "97ffe2665c1e0eb0f38c85f17ec1449c21877075",
      "total_commits": 3,
      "total_lines": 3312,
      "lang_lines": {
        "TypeScript": 3084,
        "SQL": 228
      }
    },
    "BassRhombus/primal-skins": {
      "last_sha": "d4a8ddbee7e94977e3e260c328bd979e1f0a0b69",
      "total_commits": 2,
      "total_lines": 126,
      "lang_lines": {
        "Python": 126
      }
    },
    "Taskiry/app": {
      "last_sha": "bc41a9c85a9de2078d6a22843d59d6d07a75f1ce",
      "total_commits": 16,
      "total_lines": 20079,
      "lang_lines": {
        "TypeScript": 20079
      }
    },
    "BassRhombus/skin-creator-app": {
      "last_sha": "b6a228c35026a56a56ca684a5743f090c1fcd95e",
      "total_commits": 1,
      "total_lines": 82,
      "lang_lines": {
        "JavaScript": 82
      }
    },
    "BassRhombus/primal-tickets": {
      "last_sha": "94b349ad3e4d55c75d72fb1fa68cd229fddb2117",
      "total_commits": 2,
      "total_lines": 212,
      "lang_lines": {
        "Python": 212
      }
    },
    "BassRhombus/primal-patcher": {
      "last_sha": "7c843fa19c4a473d0f48ae10485c3f520eb1520e",
      "total_commits": 1,
      "total_lines": 1045,
      "lang_lines": {
        "Python": 400,
        "Shell": 645
      }
    },
    "BassRhombus/primal-deathmatch-external": {
      "last_sha": "b1ae031e3013312a39976de08513ab1e0b1f54b1",
      "total_commits": 1,
      "total_lines": 39,
      "lang_lines": {
        "Python": 39
      }
    },
    "BassRhombus/Fan-Manager": {
      "last_sha": "ce0c436383d320131240b5afc0e5d979bc212652",
      "total_commits": 36,
      "total_lines": 17963,
      "lang_lines": {
        "TypeScript": 17963
      }
    },
    "BassRhombus/PTEggos": {
      "last_sha": "2ca4e60ee71aa957a1c85e97b976d2090501bff7",
      "total_commits": 85,
      "total_lines": 3244,
      "lang_lines": {
        "Shell": 2974,
        "Python": 270
      }
    },
    "Arvo-Devs/tasty-api": {
      "last_sha": "1b124767c3ca7eafea019550e936e948e0a9570d",
      "total_commits": 152,
      "total_lines": 62206,
      "lang_lines": {
        "TypeScript": 60621,
        "SQL": 1033,
        "JavaScript": 552
      }
    },
    "Arvo-Devs/onlysearch-backend": {
      "last_sha": "82f61782a21a3fd5b33fe7b3e419c385a4d7792f",
      "total_commits": 6,
      "total_lines": 122,
      "lang_lines": {
        "JavaScript": 122
      }
    },
    "OFManager-app/releases-dev": {
      "last_sha": "bfe4967a74af0235a9390e282dcbccf1f51e037e",
      "total_commits": 1,
      "total_lines": 0,
      "lang_lines": {}
    },
    "BassRhombus/primal-core": {
      "last_sha": "7e6cd563169744792229a965d1c8676782e6e64b",
      "total_commits": 1,
      "total_lines": 438,
      "lang_lines": {
        "Python": 438
      }
    },
    "BassRhombus/SampleListWidget": {
      "last_sha": "8b3f93cb2953dd4308aff2b7e277b0d2c275a7d0",
      "total_commits": 1,
      "total_lines": 31,
      "lang_lines": {
        "Dart": 31
      }
    },
    "BassRhombus/ShopkeepersBot": {
      "last_sha": "4c603508375e6b7d0e7dd9069c4c9cc7a836a77c",
      "total_commits": 1,
      "total_lines": 3290,
      "lang_lines": {
        "Python": 3283,
        "C": 6,
        "C++": 1
      }
    },
    "BassRhombus/Deathmatch-Template": {
      "last_sha": "03e6ff1730f9e71d82fa61c868672df478dff685",
      "total_commits": 2,
      "total_lines": 1112,
      "lang_lines": {
        "Python": 1112
      }
    },
    "BassRhombus/primal_heaven": {
      "last_sha": "52a56df19ff66718db03d4ecc67205335e464374",
      "total_commits": 17,
      "total_lines": 18280,
      "lang_lines": {
        "JavaScript": 1144,
        "TypeScript": 17042,
        "Python": 94
      }
    },
    "BassRhombus/DryReefBot": {
      "last_sha": "1ad9efae5f1d0db3ad1234b23247609e352f6ee1",
      "total_commits": 1,
      "total_lines": 9095,
      "lang_lines": {
        "Python": 9095
      }
    },
    "BassRhombus/all-onlyfans-apps-old": {
      "last_sha": "4ea4c26ee60e823bfb84c20c24c59ca9c268b05f",
      "total_commits": 1,
      "total_lines": 35121,
      "lang_lines": {
        "TypeScript": 34744,
        "Rust": 27,
        "SQL": 350
      }
    },
    "BassRhombus/Betterfans": {
      "last_sha": "157e06361f8f2df95fc9e9e85ead668645e3835d",
      "total_commits": 1,
      "total_lines": 35121,
      "lang_lines": {
        "TypeScript": 34744,
        "Rust": 27,
        "SQL": 350
      }
    },
    "Arvo-Devs/all-onlyfans-apps": {
      "last_sha": "d54e0c13bb29f988138325ddcffcbeedb4a4497d",
      "total_commits": 1,
      "total_lines": 4184,
      "lang_lines": {
        "TypeScript": 4184
      }
    },
    "Ice-Code-Games/IslaPrima": {
      "last_sha": "8082d0a45b60beee320d0d116670cd3e5b336d4d",
      "total_commits": 3,
      "total_lines": 0,
      "lang_lines": {}
    },
    "BassRhombus/IceCodes-Discordpy-Modules": {
      "last_sha": "9e11b5532404aa55db0526c0d387a5e7d515e0a6",
      "total_commits": 5,
      "total_lines": 1207,
      "lang_lines": {
        "Python": 1207
      }
    },
    "BassRhombus/IslaPrima": {
      "last_sha": "bf55417995da05881f808159a71d4500f2fde548",
      "total_commits": 1,
      "total_lines": 0,
      "lang_lines": {}
    },
    "xcodesjs/exologmanager": {
      "last_sha": "f128792735d596b82fcf3d175ba4106b95203d70",
      "total_commits": 1,
      "total_lines": 1830,
      "lang_lines": {
        "Python": 1830
      }
    },
    "BassRhombus/EvrimaBot2": {
      "last_sha": "b1b5c2c370c6c424033f4d6077acb707696a7458",
      "total_commits": 1,
      "total_lines": 8194,
      "lang_lines": {
        "Python": 8099,
        "Rust": 95
      }
    },
    "BassRhombus/TTRail": {
      "last_sha": "4d1d0165cab5bbbf9257cc826c81f3934f9a6b9f",
      "total_commits": 9,
      "total_lines": 5638,
      "lang_lines": {
        "Dart": 5010,
        "C++": 609,
        "Kotlin": 6,
        "Swift": 13
      }
    },
    "BassRhombus/BeigeBot": {
      "last_sha": "13dd39d2a82fcf8eebd793221a685ab4f5a2a667",
      "total_commits": 1,
      "total_lines": 1186,
      "lang_lines": {
        "Python": 1186
      }
    },
    "BassRhombus/TheIsleModBot": {
      "last_sha": "36ba89d4f86003532ed079f62e4f529a8ef4fdbb",
      "total_commits": 1,
      "total_lines": 41,
      "lang_lines": {
        "Python": 41
      }
    },
    "GetKrakn/kraknapi": {
      "last_sha": "bc1fbcfbe3f9022b35ade29cb9d3f357e2c84c5a",
      "total_commits": 5,
      "total_lines": 962,
      "lang_lines": {
        "Python": 962
      }
    },
    "BassRhombus/calebtrahanweb": {
      "last_sha": "b3dd347bd0357be13133152e035f5e525cbfe157",
      "total_commits": 1,
      "total_lines": 1248,
      "lang_lines": {
        "Kotlin": 6,
        "Swift": 73,
        "C++": 818,
        "Dart": 351
      }
    },
    "BassRhombus/icebotweb": {
      "last_sha": "9f02c0cecbd533cc7ae440881d489d4d5891a0d1",
      "total_commits": 5,
      "total_lines": 2764,
      "lang_lines": {
        "Dart": 1947,
        "Kotlin": 6,
        "Swift": 51,
        "C++": 760
      }
    },
    "BassRhombus/icebotweb-main": {
      "last_sha": "c84907e1587de3c748da6dca7f657dc33716f5f1",
      "total_commits": 1,
      "total_lines": 2801,
      "lang_lines": {
        "Kotlin": 6,
        "Swift": 51,
        "C++": 760,
        "Dart": 1984
      }
    },
    "BassRhombus/krakn5": {
      "last_sha": "05fb3c9204cf5a8f20697971741b27262fdb9436",
      "total_commits": 1,
      "total_lines": 19335,
      "lang_lines": {
        "Kotlin": 6,
        "Swift": 13,
        "C++": 1,
        "Dart": 19315
      }
    },
    "KraknFood/Krakn": {
      "last_sha": "fa934403805b0b3d860bd28f22c00f6b06031a05",
      "total_commits": 18,
      "total_lines": 19925,
      "lang_lines": {
        "Dart": 19188,
        "C++": 673,
        "Swift": 58,
        "Kotlin": 6
      }
    },
    "BassRhombus/Mod-Bot": {
      "last_sha": "280248b181f0fabb2a6dcef6f5e13955234e14b3",
      "total_commits": 25,
      "total_lines": 22799,
      "lang_lines": {
        "JavaScript": 22799
      }
    },
    "BassRhombus/titantech": {
      "last_sha": "48d4660a7486364ed0fbaa3786a93f8f465997c1",
      "total_commits": 165,
      "total_lines": 26306,
      "lang_lines": {
        "TypeScript": 11298,
        "JavaScript": 15008
      }
    },
    "NexLink-Core-LLC/NLC-Website": {
      "last_sha": "a7b5157ce44addaedcb4a5fc8fea6d05002993ae",
      "total_commits": 4,
      "total_lines": 0,
      "lang_lines": {}
    },
    "BassRhombus/BetterTickets": {
      "last_sha": "8534f7a95e58ec86d9520ac64e48606a987debf1",
      "total_commits": 67,
      "total_lines": 14026,
      "lang_lines": {
        "JavaScript": 14026
      }
    },
    "BassRhombus/New-folder": {
      "last_sha": "66636a84e5db457cdb4a277a9af1ecf5fbdc37ca",
      "total_commits": 68,
      "total_lines": 29648,
      "lang_lines": {
        "TypeScript": 29254,
        "JavaScript": 394
      }
    },
    "BassRhombus/BOT-0032": {
      "last_sha": "96a27b196803b18d18dc0aa39c552b6e43b04b3a",
      "total_commits": 1,
      "total_lines": 1590,
      "lang_lines": {
        "JavaScript": 1590
      }
    },
    "BassRhombus/Finances": {
      "last_sha": "6113e3c81e6acb2c828786edba5fcc449cc01b97",
      "total_commits": 8,
      "total_lines": 2494,
      "lang_lines": {
        "TypeScript": 2494
      }
    },
    "BassRhombus/AshfallBot": {
      "last_sha": "4b5ab643e143fa0a0c8ae0fdb3106e9566e357c2",
      "total_commits": 17,
      "total_lines": 5940,
      "lang_lines": {
        "JavaScript": 5940
      }
    },
    "BassRhombus/WhitelistSync": {
      "last_sha": "371893db6dd4223b10897e0230d3c6400c2dbc23",
      "total_commits": 27,
      "total_lines": 3012,
      "lang_lines": {
        "JavaScript": 3012
      }
    },
    "BassRhombus/BOT-0019": {
      "last_sha": "d09b893337792fe83ac082802a35c4aa371ce93a",
      "total_commits": 23,
      "total_lines": 5369,
      "lang_lines": {
        "JavaScript": 5369
      }
    },
    "BassRhombus/QueryBot": {
      "last_sha": "829487dd343533a8c8514d6533b39c3c46bc3595",
      "total_commits": 3,
      "total_lines": 4184,
      "lang_lines": {
        "JavaScript": 4184
      }
    },
    "BassRhombus/BOT-0029": {
      "last_sha": "996f93105ae46177b3ed88ba4c7d58140b4210ea",
      "total_commits": 4,
      "total_lines": 1619,
      "lang_lines": {
        "JavaScript": 1619
      }
    },
    "BassRhombus/DynastyBot2": {
      "last_sha": "02c9c765dd1260334cf07595b19dbeb1e38a0730",
      "total_commits": 8,
      "total_lines": 230,
      "lang_lines": {
        "JavaScript": 230
      }
    },
    "BassRhombus/BOT-0030": {
      "last_sha": "37652bf300043a71e82742eaa40b9a8ec1b619da",
      "total_commits": 5,
      "total_lines": 6160,
      "lang_lines": {
        "JavaScript": 6160
      }
    },
    "BassRhombus/BOT-0026": {
      "last_sha": "55cdcb5dc7b6f7a8772a81280afe53d64dc0dfb8",
      "total_commits": 4,
      "total_lines": 2600,
      "lang_lines": {
        "JavaScript": 2600
      }
    },
    "BassRhombus/TTBotBot": {
      "last_sha": "564c1591f77d1c2e8eaaffd121b716133179b933",
      "total_commits": 9,
      "total_lines": 5107,
      "lang_lines": {
        "JavaScript": 5107
      }
    },
    "BassRhombus/BOT-0021": {
      "last_sha": "510346047a1e2756e751acdbec221ad9a6bd00c9",
      "total_commits": 6,
      "total_lines": 811,
      "lang_lines": {
        "JavaScript": 811
      }
    },
    "BassRhombus/CustomerLink": {
      "last_sha": "f9bc1822387e5b01e71f55622c757d60910ca8af",
      "total_commits": 1,
      "total_lines": 59,
      "lang_lines": {
        "JavaScript": 59
      }
    },
    "BassRhombus/BOT-0007": {
      "last_sha": "07d3eac25590c27cde21b24adb4ba8c4e0a328b3",
      "total_commits": 16,
      "total_lines": 7592,
      "lang_lines": {
        "JavaScript": 7592
      }
    },
    "BassRhombus/BOT-0022": {
      "last_sha": "d28d192c19c7fd849854e5abe28271eb42c04280",
      "total_commits": 2,
      "total_lines": 719,
      "lang_lines": {
        "JavaScript": 719
      }
    },
    "BassRhombus/DiscordFix": {
      "last_sha": "309dc74869169ed3ff6a7980a1033e420d5aa136",
      "total_commits": 3,
      "total_lines": 408,
      "lang_lines": {
        "JavaScript": 408
      }
    },
    "BassRhombus/PteroImages": {
      "last_sha": "f36bc90d8e15a793bf00f374268ec598f813bcc4",
      "total_commits": 5,
      "total_lines": 324,
      "lang_lines": {
        "Shell": 324
      }
    },
    "BassRhombus/BassPanel": {
      "last_sha": "0421524ab2b4f720be77381411949b7c4223a0be",
      "total_commits": 12,
      "total_lines": 9897,
      "lang_lines": {
        "JavaScript": 9897
      }
    },
    "BassRhombus/BOT-0023": {
      "last_sha": "58d2fbf76dacb4e54e6bbfd80f3e62d9c5e145a6",
      "total_commits": 14,
      "total_lines": 323,
      "lang_lines": {
        "JavaScript": 323
      }
    },
    "BassRhombus/BOT-0020": {
      "last_sha": "e9866f9904cd97b0f8c490d3856fa8dc24fe692c",
      "total_commits": 5,
      "total_lines": 7115,
      "lang_lines": {
        "JavaScript": 7088,
        "SQL": 27
      }
    },
    "BassRhombus/DynastyBot-Customer": {
      "last_sha": "6ef9483b44976cda8288954f2e7bf09c8ef07958",
      "total_commits": 15,
      "total_lines": 2777,
      "lang_lines": {
        "JavaScript": 2777
      }
    },
    "BassRhombus/GalaxyBot": {
      "last_sha": "38bca0ef1f1ab4f9b9027e3a8256c918a1813ef3",
      "total_commits": 14,
      "total_lines": 1405,
      "lang_lines": {
        "JavaScript": 1405
      }
    },
    "BassRhombus/CustomerBotMonitor": {
      "last_sha": "9e228cf7febb7042c4d0c57783247552dfa4d3f2",
      "total_commits": 1,
      "total_lines": 286,
      "lang_lines": {
        "JavaScript": 286
      }
    },
    "BassRhombus/BOT-0016": {
      "last_sha": "6b77f731fba508470367abd27be4637edeadcee8",
      "total_commits": 8,
      "total_lines": 1311,
      "lang_lines": {
        "JavaScript": 1311
      }
    },
    "BassRhombus/UselessSite": {
      "last_sha": "033806be35681312988030788506ef1a728fdb6c",
      "total_commits": 1,
      "total_lines": 779,
      "lang_lines": {
        "JavaScript": 779
      }
    },
    "BassRhombus/DiscordServerTracker": {
      "last_sha": "629f537ae37adc61b5d8136a5adfd964eb9e89fc",
      "total_commits": 11,
      "total_lines": 2181,
      "lang_lines": {
        "JavaScript": 2181
      }
    },
    "BassRhombus/NewBassLicense": {
      "last_sha": "71fb7ded14f983e395f46ce557c2429a87397231",
      "total_commits": 61,
      "total_lines": 36735,
      "lang_lines": {
        "JavaScript": 21833,
        "TypeScript": 14009,
        "SQL": 836,
        "Shell": 57
      }
    },
    "BassRhombus/GSH-Image-Bin": {
      "last_sha": "a54c2a4ed8d45f962dffc0fd8e50c2fb010560f6",
      "total_commits": 3,
      "total_lines": 976,
      "lang_lines": {
        "JavaScript": 953,
        "SQL": 23
      }
    },
    "BassRhombus/DuelBot": {
      "last_sha": "d7e951f46c327b704bc9483f39e5d1b444d2ea60",
      "total_commits": 3,
      "total_lines": 2536,
      "lang_lines": {
        "JavaScript": 2536
      }
    },
    "BassRhombus/BOT-0011": {
      "last_sha": "afca84c99ec3fd0dc57961ed15b21faed9e0a6a5",
      "total_commits": 1,
      "total_lines": 602,
      "lang_lines": {
        "JavaScript": 602
      }
    },
    "BassRhombus/SpeciesTracker": {
      "last_sha": "8d7b03c60466b238c2fc2e8a76a814779c792e4c",
      "total_commits": 1,
      "total_lines": 1553,
      "lang_lines": {
        "JavaScript": 1553
      }
    },
    "BassRhombus/DynastyBot": {
      "last_sha": "d6d49faeabf8be0bf95069cd5c6244610c6b4afa",
      "total_commits": 3,
      "total_lines": 583,
      "lang_lines": {
        "JavaScript": 583
      }
    },
    "BassRhombus/SentryBot": {
      "last_sha": "3d667764fb3f8889705fd13da9aca23726fdc83d",
      "total_commits": 1,
      "total_lines": 6839,
      "lang_lines": {
        "JavaScript": 6839
      }
    },
    "BassRhombus/BetterLicenseBot": {
      "last_sha": "e156cfdbb903cfcdfe5eb96f3dc5049791ab03d5",
      "total_commits": 69,
      "total_lines": 5579,
      "lang_lines": {
        "JavaScript": 5579
      }
    },
    "BassRhombus/SupportBot": {
      "last_sha": "5423b4db4557eedf2a273351f8b7cd58cf3a913d",
      "total_commits": 1,
      "total_lines": 448,
      "lang_lines": {
        "JavaScript": 448
      }
    },
    "BassRhombus/MoxhaBot": {
      "last_sha": "c3688a91d9635951f9d31dd4aedbb1c238003d61",
      "total_commits": 4,
      "total_lines": 966,
      "lang_lines": {
        "JavaScript": 966
      }
    },
    "BassRhombus/TempBot": {
      "last_sha": "3dc5186035f7ca8e719e04ea8641b6aa6b8baeea",
      "total_commits": 1,
      "total_lines": 417,
      "lang_lines": {
        "JavaScript": 417
      }
    },
    "BassRhombus/MinneyBot": {
      "last_sha": "20e5d657ecfc583b3a816dd3dfa8593533c2189a",
      "total_commits": 5,
      "total_lines": 4923,
      "lang_lines": {
        "JavaScript": 4923
      }
    },
    "BassRhombus/WaitingBot": {
      "last_sha": "a3f061250e5f68c8aaa291cc8566783384f200fb",
      "total_commits": 4,
      "total_lines": 554,
      "lang_lines": {
        "JavaScript": 554
      }
    },
    "BassRhombus/MisfitsStrikeBot": {
      "last_sha": "85ae8de484530a18198ee335a7e47a1d8052309c",
      "total_commits": 44,
      "total_lines": 7141,
      "lang_lines": {
        "JavaScript": 7141
      }
    },
    "BassRhombus/ISLNotes": {
      "last_sha": "bf2dc061a3fbc1085a02a5caa6e68445672e4911",
      "total_commits": 1,
      "total_lines": 0,
      "lang_lines": {}
    },
    "BassRhombus/APICaller": {
      "last_sha": "287b2a80b069b48c1b43929f0ae470264d8b4e40",
      "total_commits": 1,
      "total_lines": 505,
      "lang_lines": {
        "JavaScript": 505
      }
    },
    "BassRhombus/HermitBot": {
      "last_sha": "9e93f6c27d69f9b759fc5c837aebb439fa91977d",
      "total_commits": 33,
      "total_lines": 10036,
      "lang_lines": {
        "JavaScript": 10024,
        "Shell": 12
      }
    },
    "BassRhombus/OracleBot": {
      "last_sha": "c67a84b5de98cab17bc6aeaec6cd28d726b6d19b",
      "total_commits": 13,
      "total_lines": 146,
      "lang_lines": {
        "JavaScript": 146
      }
    },
    "BassRhombus/PteroServerBot": {
      "last_sha": "b787f9b5710880f00487e6fcd64dff3a514aa321",
      "total_commits": 27,
      "total_lines": 4723,
      "lang_lines": {
        "JavaScript": 4723
      }
    },
    "BassRhombus/Reaverbot2.0": {
      "last_sha": "21f9e9343d88b38dd4b00adfc16a4e55064a1521",
      "total_commits": 22,
      "total_lines": 1164,
      "lang_lines": {
        "JavaScript": 1164
      }
    },
    "BassRhombus/LizardBot": {
      "last_sha": "9165d983807c69a9503555f5224175db44d61f84",
      "total_commits": 2,
      "total_lines": 41,
      "lang_lines": {
        "JavaScript": 41
      }
    },
    "BassRhombus/ReaverBot": {
      "last_sha": "28c5cfeda91c78bcf9be3b52783e4fa198249adc",
      "total_commits": 33,
      "total_lines": 4371,
      "lang_lines": {
        "JavaScript": 4301,
        "Python": 70
      }
    },
    "BassRhombus/InviteBot": {
      "last_sha": "232f38d67f96896ba2a4ba964e650d581b433a04",
      "total_commits": 3,
      "total_lines": 1064,
      "lang_lines": {
        "JavaScript": 1064
      }
    },
    "BassRhombus/ApexArchon": {
      "last_sha": "5ab940b49d6a732d1bbed77b1804c6a58d9111d6",
      "total_commits": 111,
      "total_lines": 4193,
      "lang_lines": {
        "JavaScript": 4193
      }
    },
    "BassRhombus/BassAPI": {
      "last_sha": "b5bdae48bc47b455f6a525a3fae6ed733bfffef5",
      "total_commits": 6,
      "total_lines": 443,
      "lang_lines": {
        "JavaScript": 438,
        "Shell": 5
      }
    },
    "BassRhombus/PBugTrack": {
      "last_sha": "9f68afa4890e1277cce43d675ddce86db4981e1c",
      "total_commits": 6,
      "total_lines": 584,
      "lang_lines": {
        "JavaScript": 584
      }
    },
    "BassRhombus/StenopsBot": {
      "last_sha": "dd36d7414b46a5ee238c428dab017c9f5bc86024",
      "total_commits": 8,
      "total_lines": 1288,
      "lang_lines": {
        "JavaScript": 1288
      }
    },
    "BassRhombus/PHPKillTracker": {
      "last_sha": "c5f3d75ef80a0c78d729e0b7e465035aacffef62",
      "total_commits": 7,
      "total_lines": 1240,
      "lang_lines": {
        "JavaScript": 1240
      }
    },
    "BassRhombus/NPM": {
      "last_sha": "99cbceaf33e16ebdbf0bf508b0210ae84e1e29d5",
      "total_commits": 2,
      "total_lines": 442,
      "lang_lines": {
        "JavaScript": 442
      }
    },
    "BassRhombus/AdminApp": {
      "last_sha": "32c2a33e0bbeb342fbb0c58e4fd1539b1da8870f",
      "total_commits": 4,
      "total_lines": 1364,
      "lang_lines": {
        "JavaScript": 1364
      }
    },
    "BassRhombus/PrehistoricBotV2": {
      "last_sha": "1805dcd6d2e7b44479205ae52e1f04e0577b85d6",
      "total_commits": 53,
      "total_lines": 8260,
      "lang_lines": {
        "JavaScript": 8260
      }
    },
    "BassRhombus/modAPIpull": {
      "last_sha": "8c219d2ccdad81aca6d256365d369f684310f27f",
      "total_commits": 5,
      "total_lines": 318,
      "lang_lines": {
        "JavaScript": 301,
        "Python": 17
      }
    },
    "BassRhombus/beta-bot": {
      "last_sha": "17678de8fa968517a4856f77463e49dd9fda5ced",
      "total_commits": 4,
      "total_lines": 838,
      "lang_lines": {
        "JavaScript": 838
      }
    },
    "BassRhombus/draconia-egg": {
      "last_sha": "82a51c9c229bb0ffc50990aabfb739d689884963",
      "total_commits": 2,
      "total_lines": 51,
      "lang_lines": {
        "Shell": 51
      }
    },
    "BassRhombus/JSBotWGSM": {
      "last_sha": "47761c6751ecd608c34ca233054705a22b219c6b",
      "total_commits": 4,
      "total_lines": 402,
      "lang_lines": {
        "C#": 402
      }
    },
    "BassRhombus/DMSuggestions": {
      "last_sha": "a542fec70c9faa47ef92eca939a3db40ee32b85f",
      "total_commits": 6,
      "total_lines": 862,
      "lang_lines": {
        "JavaScript": 862
      }
    },
    "BassRhombus/ChatBot": {
      "last_sha": "3698d00cc60f9eaaaad0c1e80b0976aa623a5f73",
      "total_commits": 7,
      "total_lines": 441,
      "lang_lines": {
        "JavaScript": 441
      }
    },
    "BassRhombus/ModIniGen": {
      "last_sha": "5a13b1fcd9e791b918841d696de0f967bc016c80",
      "total_commits": 1,
      "total_lines": 18,
      "lang_lines": {
        "JavaScript": 18
      }
    },
    "BassRhombus/GroupChat": {
      "last_sha": "c515653330a91d25b16c7189cef4a421157a1d66",
      "total_commits": 1,
      "total_lines": 46,
      "lang_lines": {
        "JavaScript": 46
      }
    },
    "BassRhombus/AISite": {
      "last_sha": "e71112905075f1440906330708f1d1a29f2a8ecd",
      "total_commits": 5,
      "total_lines": 83,
      "lang_lines": {
        "JavaScript": 83
      }
    },
    "BassRhombus/DawnBot": {
      "last_sha": "7fcac83932ab73fc3a4df929fb265801e997de69",
      "total_commits": 3,
      "total_lines": 486,
      "lang_lines": {
        "JavaScript": 486
      }
    },
    "BassRhombus/Scheduler": {
      "last_sha": "0b6b9af73dc0d7357349293543ae1e67d97b46e7",
      "total_commits": 10,
      "total_lines": 1574,
      "lang_lines": {
        "JavaScript": 1574
      }
    },
    "BassRhombus/PoTRconBot": {
      "last_sha": "b29eccbf94e3e860e5eaf6cd8648bfd89842fa45",
      "total_commits": 7,
      "total_lines": 2320,
      "lang_lines": {
        "JavaScript": 2320
      }
    },
    "BassRhombus/PrehistoricBot": {
      "last_sha": "cdc90a470e6bdca41d273a82739e4cfc110726fa",
      "total_commits": 30,
      "total_lines": 2768,
      "lang_lines": {
        "JavaScript": 2768
      }
    },
    "BassRhombus/TriBot": {
      "last_sha": "e6af151f7536368817bb0f646c7cfc86c3276358",
      "total_commits": 14,
      "total_lines": 3682,
      "lang_lines": {
        "JavaScript": 3682
      }
    },
    "BassRhombus/INI-Generator": {
      "last_sha": "cecfb40d29e3d5d373a1b7bf52c08e424fe435ba",
      "total_commits": 1,
      "total_lines": 876,
      "lang_lines": {
        "JavaScript": 876
      }
    }
  }
}